dxc/__init__.py
dxc/ai/__init__.py
dxc/ai/AI_guild/AI_guild.py
dxc/ai/AI_guild/__init__.py
dxc/ai/clean_data/__init__.py
dxc/ai/clean_data/clean_data.py
dxc/ai/datasets/__init__.py
dxc/ai/datasets/_base.py
dxc/ai/deep_learning/__init__.py
dxc/ai/deep_learning/image_classifier.py
dxc/ai/deploy_app/__init__.py
dxc/ai/deploy_app/build_app.py
dxc/ai/deploy_app/deploy_modelfiles.py
dxc/ai/deploy_app/retrieve_modelfiles.py
dxc/ai/global_variables/__init__.py
dxc/ai/global_variables/globals_file.py
dxc/ai/logging/__init__.py
dxc/ai/logging/experiment_design_logging.py
dxc/ai/logging/microservice_logging.py
dxc/ai/logging/pipeline_logging.py
dxc/ai/pipeline/__init__.py
dxc/ai/pipeline/pipeline.py
dxc/ai/publish_microservice/__init__.py
dxc/ai/publish_microservice/publish_microservice.py
dxc/ai/publish_microservice/publish_new_microservice.py
dxc/ai/read_data/__init__.py
dxc/ai/read_data/read_csv.py
dxc/ai/read_data/read_excel.py
dxc/ai/read_data/read_json.py
dxc/ai/run_model/TimeSeriesModels.py
dxc/ai/run_model/__init__.py
dxc/ai/run_model/clustering.py
dxc/ai/run_model/interpret_model.py
dxc/ai/run_model/model_pipeline.py
dxc/ai/run_model/run_model.py
dxc/ai/sentiment_analysis/__init__.py
dxc/ai/sentiment_analysis/sentiment_analysis.py
dxc/ai/unsupervised_sentiment_analysis/__init__.py
dxc/ai/unsupervised_sentiment_analysis/kmeans_sentiment_analysis.py
dxc/ai/visualization/__init__.py
dxc/ai/visualization/visualization.py
dxc/rl/__init__.py
dxc/rl/rl_helper_function/__init__.py
dxc/rl/rl_helper_function/define_model_components.py
dxc/rl/rl_helper_function/helper_function.py
DXC_Industrialized_AI_Starter-3.2.0.dist-info/LICENSE
DXC_Industrialized_AI_Starter-3.2.0.dist-info/METADATA
DXC_Industrialized_AI_Starter-3.2.0.dist-info/WHEEL
DXC_Industrialized_AI_Starter-3.2.0.dist-info/entry_points.txt
DXC_Industrialized_AI_Starter-3.2.0.dist-info/top_level.txt
DXC_Industrialized_AI_Starter-3.2.0.dist-info/RECORD
