Metadata-Version: 2.1
Name: DXC-Industrialized-AI-Starter
Version: 3.2.0
Summary: Python library which is extensively used for all AI projects
Home-page: https://github.com/dxc-technology/DXC-Industrialized-AI-Starter
Author: DXC
License: Apache License 2.0
Platform: any
Classifier: License :: OSI Approved :: Apache Software License
Classifier: Programming Language :: Python :: 3.7
License-File: LICENSE
Requires-Dist: TPOT (==0.11.7)
Requires-Dist: yellowbrick (==1.4)
Requires-Dist: scrubadub (==1.2.2)
Requires-Dist: feature-engine (==1.2.0)
Requires-Dist: pymongo (==4.0.1)
Requires-Dist: pmdarima (==1.8.4)
Requires-Dist: ftfy (==6.0.3)
Requires-Dist: interpret-community (==0.24.2)
Requires-Dist: missingno (==0.5.0)
Requires-Dist: arrow (==1.1.1)
Requires-Dist: pyjanitor (==0.20.0)
Requires-Dist: pyaf (==3.0)
Requires-Dist: pandas-profiling (==3.0.0)
Requires-Dist: datacleaner (==0.1.5)
Requires-Dist: GitPython (==3.1.27)
Requires-Dist: ipython (>=7.16.1)
Requires-Dist: raiwidgets (==0.9.4)
Requires-Dist: scikit-learn
Requires-Dist: flatten-json (==0.1.13)
Requires-Dist: sqlalchemy (==1.3.24)
Requires-Dist: dnspython (==2.1.0)
Requires-Dist: pytest (==6.0.1)
Requires-Dist: PyGithub
Requires-Dist: google-api-python-client
